{
  "generator-jhipster": {
    "applicationType": "monolith",
    "authenticationType": "jwt",
    "baseName": "angular",
    "blueprints": [],
    "buildTool": "maven",
    "cacheProvider": "ehcache",
    "clientFramework": "angularX",
    "clientPackageManager": "npm",
    "clientTheme": "none",
    "clientThemeVariant": "",
    "creationTimestamp": 1682778377383,
    "databaseType": "sql",
    "devDatabaseType": "h2Disk",
    "devServerPort": 4200,
    "dtoSuffix": "DTO",
    "enableGradleEnterprise": false,
    "enableHibernateCache": true,
    "enableSwaggerCodegen": false,
    "enableTranslation": true,
    "entitySuffix": "",
    "jhiPrefix": "jhi",
    "jhipsterVersion": "7.9.3",
    "jwtSecretKey": "MjBhMzMyZDMwYjBlNDMxNDc2OGM5NDAzNmFiYzQxZTY5MmM3NTU3MGVlYzlkOTIxYzJlNWQ4ZTZlMmQ4MWEyMGEzMmEzODgxNGE2MWU0YmEyODhhYTE0YmRmMzExMzBjZjlmMTY5Y2MyMTgwOGY0ZTIzMGZjZWFmM2M2NTE0Yjc=",
    "languages": ["en"],
    "messageBroker": "kafka",
    "microfrontend": false,
    "microfrontends": [],
    "nativeLanguage": "en",
    "otherModules": [],
    "packageName": "com.panthera",
    "pages": [],
    "prodDatabaseType": "postgresql",
    "reactive": false,
    "searchEngine": "elasticsearch",
    "serverPort": "8080",
    "serverSideOptions": ["searchEngine:elasticsearch", "websocket:spring-websocket", "messageBroker:kafka"],
    "serviceDiscoveryType": "eureka",
    "skipCheckLengthOfIdentifier": false,
    "skipClient": false,
    "skipFakeData": false,
    "skipUserManagement": false,
    "testFrameworks": [],
    "websocket": "spring-websocket",
    "withAdminUi": true
  }
}
